<?xml version="1.0"?>
<!DOCTYPE pathway SYSTEM "https://www.kegg.jp/kegg/xml/KGML_v0.7.2_.dtd">
<!-- Creation date: Jan 20, 2022 16:55:15 +0900 (GMT+9) -->
<pathway name="path:cla00780" org="cla" number="00780"
         title="Biotin metabolism"
         image="https://www.kegg.jp/kegg/pathway/cla/cla00780.png"
         link="https://www.kegg.jp/kegg-bin/show_pathway?cla00780">
    <entry id="2" name="path:map00960" type="map"
        link="https://www.kegg.jp/dbget-bin/www_bget?map00960">
        <graphics name="Tropane, piperidine and pyridine alkaloid biosynthesis" fgcolor="#000000" bgcolor="#FFFFFF"
             type="roundrectangle" x="95" y="851" width="136" height="45"/>
    </entry>
    <entry id="3" name="path:cla00780" type="map"
        link="https://www.kegg.jp/dbget-bin/www_bget?cla00780">
        <graphics name="TITLE:Biotin metabolism" fgcolor="#000000" bgcolor="#FFFFFF"
             type="roundrectangle" x="128" y="58" width="176" height="25"/>
    </entry>
    <entry id="4" name="path:cla00310" type="map"
        link="https://www.kegg.jp/dbget-bin/www_bget?cla00310">
        <graphics name="Lysine degradation" fgcolor="#000000" bgcolor="#FFFFFF"
             type="roundrectangle" x="105" y="812" width="116" height="25"/>
    </entry>
    <entry id="5" name="cpd:C02656" type="compound"
        link="https://www.kegg.jp/dbget-bin/www_bget?C02656">
        <graphics name="C02656" fgcolor="#000000" bgcolor="#FFFFFF"
             type="circle" x="582" y="351" width="8" height="8"/>
    </entry>
    <entry id="6" name="cpd:C01063" type="compound"
        link="https://www.kegg.jp/dbget-bin/www_bget?C01063">
        <graphics name="C01063" fgcolor="#000000" bgcolor="#FFFFFF"
             type="circle" x="582" y="462" width="8" height="8"/>
    </entry>
    <entry id="7" name="cpd:C01092" type="compound"
        link="https://www.kegg.jp/dbget-bin/www_bget?C01092">
        <graphics name="C01092" fgcolor="#000000" bgcolor="#FFFFFF"
             type="circle" x="414" y="528" width="8" height="8"/>
    </entry>
    <entry id="8" name="cpd:C01909" type="compound"
        link="https://www.kegg.jp/dbget-bin/www_bget?C01909">
        <graphics name="C01909" fgcolor="#000000" bgcolor="#FFFFFF"
             type="circle" x="414" y="724" width="8" height="8"/>
    </entry>
    <entry id="9" name="cpd:C01037" type="compound"
        link="https://www.kegg.jp/dbget-bin/www_bget?C01037">
        <graphics name="C01037" fgcolor="#000000" bgcolor="#FFFFFF"
             type="circle" x="414" y="594" width="8" height="8"/>
    </entry>
    <entry id="10" name="cpd:C00120" type="compound"
        link="https://www.kegg.jp/dbget-bin/www_bget?C00120">
        <graphics name="C00120" fgcolor="#000000" bgcolor="#FFFFFF"
             type="circle" x="414" y="791" width="8" height="8"/>
    </entry>
    <entry id="11" name="cpd:C00047" type="compound"
        link="https://www.kegg.jp/dbget-bin/www_bget?C00047">
        <graphics name="C00047" fgcolor="#000000" bgcolor="#FFFFFF"
             type="circle" x="238" y="811" width="8" height="8"/>
    </entry>
    <entry id="12" name="cpd:C05552" type="compound"
        link="https://www.kegg.jp/dbget-bin/www_bget?C05552">
        <graphics name="C05552" fgcolor="#000000" bgcolor="#FFFFFF"
             type="circle" x="280" y="857" width="8" height="8"/>
    </entry>
    <entry id="13" name="cpd:C01894" type="compound"
        link="https://www.kegg.jp/dbget-bin/www_bget?C01894">
        <graphics name="C01894" fgcolor="#000000" bgcolor="#FFFFFF"
             type="circle" x="512" y="884" width="8" height="8"/>
    </entry>
    <entry id="14" name="cpd:C05921" type="compound"
        link="https://www.kegg.jp/dbget-bin/www_bget?C05921">
        <graphics name="C05921" fgcolor="#000000" bgcolor="#FFFFFF"
             type="circle" x="414" y="884" width="8" height="8"/>
    </entry>
    <entry id="15" name="cpd:C06250" type="compound"
        link="https://www.kegg.jp/dbget-bin/www_bget?C06250">
        <graphics name="C06250" fgcolor="#000000" bgcolor="#FFFFFF"
             type="circle" x="280" y="929" width="8" height="8"/>
    </entry>
    <entry id="27" name="ko:K01942" type="ortholog" reaction="rn:R01074"
        link="https://www.kegg.jp/dbget-bin/www_bget?K01942">
        <graphics name="K01942" fgcolor="#000000" bgcolor="#FFFFFF"
             type="rectangle" x="341" y="829" width="46" height="17"/>
    </entry>
    <entry id="28" name="ko:K01942" type="ortholog" reaction="rn:R05145"
        link="https://www.kegg.jp/dbget-bin/www_bget?K01942">
        <graphics name="K01942" fgcolor="#000000" bgcolor="#FFFFFF"
             type="rectangle" x="330" y="940" width="46" height="17"/>
    </entry>
    <entry id="29" name="cla:CLA_0187" type="gene" reaction="rn:R05145"
        link="https://www.kegg.jp/dbget-bin/www_bget?cla:CLA_0187">
        <graphics name="birA" fgcolor="#000000" bgcolor="#BFFFBF"
             type="rectangle" x="378" y="940" width="46" height="17"/>
    </entry>
    <entry id="30" name="ko:K01942" type="ortholog" reaction="rn:R05145"
        link="https://www.kegg.jp/dbget-bin/www_bget?K01942">
        <graphics name="K01942" fgcolor="#000000" bgcolor="#FFFFFF"
             type="rectangle" x="330" y="919" width="46" height="17"/>
    </entry>
    <entry id="31" name="cla:CLA_0187" type="gene" reaction="rn:R01074"
        link="https://www.kegg.jp/dbget-bin/www_bget?cla:CLA_0187">
        <graphics name="birA" fgcolor="#000000" bgcolor="#BFFFBF"
             type="rectangle" x="389" y="848" width="46" height="17"/>
    </entry>
    <entry id="32" name="ko:K01942" type="ortholog" reaction="rn:R01074"
        link="https://www.kegg.jp/dbget-bin/www_bget?K01942">
        <graphics name="K01942" fgcolor="#000000" bgcolor="#FFFFFF"
             type="rectangle" x="341" y="848" width="46" height="17"/>
    </entry>
    <entry id="33" name="cla:CLA_0160" type="gene" reaction="rn:R01078"
        link="https://www.kegg.jp/dbget-bin/www_bget?cla:CLA_0160">
        <graphics name="bioB" fgcolor="#000000" bgcolor="#BFFFBF"
             type="rectangle" x="414" y="751" width="46" height="17"/>
    </entry>
    <entry id="34" name="cla:CLA_1389" type="gene" reaction="rn:R12934"
        link="https://www.kegg.jp/dbget-bin/www_bget?cla:CLA_1389">
        <graphics name="bioD" fgcolor="#000000" bgcolor="#BFFFBF"
             type="rectangle" x="414" y="687" width="46" height="17"/>
    </entry>
    <entry id="35" name="cla:CLA_1388" type="gene" reaction="rn:R03231"
        link="https://www.kegg.jp/dbget-bin/www_bget?cla:CLA_1388">
        <graphics name="bioA" fgcolor="#000000" bgcolor="#BFFFBF"
             type="rectangle" x="389" y="558" width="46" height="17"/>
    </entry>
    <entry id="37" name="cla:CLA_1386" type="gene" reaction="rn:R03210"
        link="https://www.kegg.jp/dbget-bin/www_bget?cla:CLA_1386">
        <graphics name="bioF" fgcolor="#000000" bgcolor="#BFFFBF"
             type="rectangle" x="583" y="493" width="46" height="17"/>
    </entry>
    <entry id="38" name="ko:K01906" type="ortholog" reaction="rn:R03209"
        link="https://www.kegg.jp/dbget-bin/www_bget?K01906">
        <graphics name="K01906" fgcolor="#000000" bgcolor="#FFFFFF"
             type="rectangle" x="583" y="405" width="46" height="17"/>
    </entry>
    <entry id="39" name="ko:K01942" type="ortholog" reaction="rn:R05145"
        link="https://www.kegg.jp/dbget-bin/www_bget?K01942">
        <graphics name="K01942" fgcolor="#000000" bgcolor="#FFFFFF"
             type="rectangle" x="378" y="919" width="46" height="17"/>
    </entry>
    <entry id="42" name="ko:K01942" type="ortholog" reaction="rn:R01074"
        link="https://www.kegg.jp/dbget-bin/www_bget?K01942">
        <graphics name="K01942" fgcolor="#000000" bgcolor="#FFFFFF"
             type="rectangle" x="389" y="829" width="46" height="17"/>
    </entry>
    <entry id="43" name="cpd:C19845" type="compound"
        link="https://www.kegg.jp/dbget-bin/www_bget?C19845">
        <graphics name="C19845" fgcolor="#000000" bgcolor="#FFFFFF"
             type="circle" x="414" y="462" width="8" height="8"/>
    </entry>
    <entry id="45" name="cla:CLA_1385" type="gene" reaction="rn:R09725"
        link="https://www.kegg.jp/dbget-bin/www_bget?cla:CLA_1385">
        <graphics name="CLA_1385" fgcolor="#000000" bgcolor="#BFFFBF"
             type="rectangle" x="352" y="463" width="46" height="17"/>
    </entry>
    <entry id="46" name="cpd:C19846" type="compound"
        link="https://www.kegg.jp/dbget-bin/www_bget?C19846">
        <graphics name="C19846" fgcolor="#000000" bgcolor="#FFFFFF"
             type="circle" x="293" y="462" width="8" height="8"/>
    </entry>
    <entry id="48" name="cla:CLA_1386" type="gene" reaction="rn:R10124"
        link="https://www.kegg.jp/dbget-bin/www_bget?cla:CLA_1386">
        <graphics name="bioF" fgcolor="#000000" bgcolor="#BFFFBF"
             type="rectangle" x="415" y="493" width="46" height="17"/>
    </entry>
    <entry id="49" name="cpd:C01209" type="compound"
        link="https://www.kegg.jp/dbget-bin/www_bget?C01209">
        <graphics name="C01209" fgcolor="#000000" bgcolor="#FFFFFF"
             type="circle" x="118" y="141" width="8" height="8"/>
    </entry>
    <entry id="50" name="cpd:C19673" type="compound"
        link="https://www.kegg.jp/dbget-bin/www_bget?C19673">
        <graphics name="C19673" fgcolor="#000000" bgcolor="#FFFFFF"
             type="circle" x="118" y="207" width="8" height="8"/>
    </entry>
    <entry id="52" name="cla:CLA_1384" type="gene" reaction="rn:R09543"
        link="https://www.kegg.jp/dbget-bin/www_bget?cla:CLA_1384">
        <graphics name="bioC" fgcolor="#000000" bgcolor="#BFFFBF"
             type="rectangle" x="118" y="172" width="46" height="17"/>
    </entry>
    <entry id="54" name="cpd:C20372" type="compound"
        link="https://www.kegg.jp/dbget-bin/www_bget?C20372">
        <graphics name="C20372" fgcolor="#000000" bgcolor="#FFFFFF"
             type="circle" x="178" y="264" width="8" height="8"/>
    </entry>
    <entry id="56" name="cla:CLA_0269" type="gene" reaction="rn:R10116"
        link="https://www.kegg.jp/dbget-bin/www_bget?cla:CLA_0269">
        <graphics name="fabG" fgcolor="#000000" bgcolor="#BFFFBF"
             type="rectangle" x="179" y="295" width="46" height="17"/>
    </entry>
    <entry id="57" name="cpd:C20373" type="compound"
        link="https://www.kegg.jp/dbget-bin/www_bget?C20373">
        <graphics name="C20373" fgcolor="#000000" bgcolor="#FFFFFF"
             type="circle" x="178" y="330" width="8" height="8"/>
    </entry>
    <entry id="59" name="cla:CLA_1399" type="gene" reaction="rn:R10117"
        link="https://www.kegg.jp/dbget-bin/www_bget?cla:CLA_1399">
        <graphics name="fabZ" fgcolor="#000000" bgcolor="#BFFFBF"
             type="rectangle" x="179" y="361" width="46" height="17"/>
    </entry>
    <entry id="60" name="cpd:C20374" type="compound"
        link="https://www.kegg.jp/dbget-bin/www_bget?C20374">
        <graphics name="C20374" fgcolor="#000000" bgcolor="#FFFFFF"
             type="circle" x="178" y="396" width="8" height="8"/>
    </entry>
    <entry id="62" name="ko:K00208" type="ortholog" reaction="rn:R10118"
        link="https://www.kegg.jp/dbget-bin/www_bget?K00208">
        <graphics name="K00208" fgcolor="#000000" bgcolor="#FFFFFF"
             type="rectangle" x="179" y="427" width="46" height="17"/>
    </entry>
    <entry id="63" name="cpd:C20375" type="compound"
        link="https://www.kegg.jp/dbget-bin/www_bget?C20375">
        <graphics name="C20375" fgcolor="#000000" bgcolor="#FFFFFF"
             type="circle" x="178" y="462" width="8" height="8"/>
    </entry>
    <entry id="67" name="ko:K00647" type="ortholog" reaction="rn:R10119"
        link="https://www.kegg.jp/dbget-bin/www_bget?K00647">
        <graphics name="K00647" fgcolor="#000000" bgcolor="#FFFFFF"
             type="rectangle" x="268" y="229" width="46" height="17"/>
    </entry>
    <entry id="68" name="cpd:C20376" type="compound"
        link="https://www.kegg.jp/dbget-bin/www_bget?C20376">
        <graphics name="C20376" fgcolor="#000000" bgcolor="#FFFFFF"
             type="circle" x="293" y="264" width="8" height="8"/>
    </entry>
    <entry id="70" name="cla:CLA_0269" type="gene" reaction="rn:R10120"
        link="https://www.kegg.jp/dbget-bin/www_bget?cla:CLA_0269">
        <graphics name="fabG" fgcolor="#000000" bgcolor="#BFFFBF"
             type="rectangle" x="294" y="295" width="46" height="17"/>
    </entry>
    <entry id="71" name="cpd:C20377" type="compound"
        link="https://www.kegg.jp/dbget-bin/www_bget?C20377">
        <graphics name="C20377" fgcolor="#000000" bgcolor="#FFFFFF"
             type="circle" x="293" y="330" width="8" height="8"/>
    </entry>
    <entry id="73" name="cla:CLA_1399" type="gene" reaction="rn:R10121"
        link="https://www.kegg.jp/dbget-bin/www_bget?cla:CLA_1399">
        <graphics name="fabZ" fgcolor="#000000" bgcolor="#BFFFBF"
             type="rectangle" x="294" y="361" width="46" height="17"/>
    </entry>
    <entry id="74" name="cpd:C20378" type="compound"
        link="https://www.kegg.jp/dbget-bin/www_bget?C20378">
        <graphics name="C20378" fgcolor="#000000" bgcolor="#FFFFFF"
             type="circle" x="293" y="396" width="8" height="8"/>
    </entry>
    <entry id="76" name="ko:K00208" type="ortholog" reaction="rn:R10122"
        link="https://www.kegg.jp/dbget-bin/www_bget?K00208">
        <graphics name="K00208" fgcolor="#000000" bgcolor="#FFFFFF"
             type="rectangle" x="294" y="427" width="46" height="17"/>
    </entry>
    <entry id="77" name="cla:CLA_0286" type="gene" reaction="rn:R10119"
        link="https://www.kegg.jp/dbget-bin/www_bget?cla:CLA_0286">
        <graphics name="fabF" fgcolor="#000000" bgcolor="#BFFFBF"
             type="rectangle" x="318" y="229" width="46" height="17"/>
    </entry>
    <entry id="79" name="ko:K16593" type="ortholog" reaction="rn:R10123"
        link="https://www.kegg.jp/dbget-bin/www_bget?K16593">
        <graphics name="K16593" fgcolor="#000000" bgcolor="#FFFFFF"
             type="rectangle" x="415" y="405" width="46" height="17"/>
    </entry>
    <entry id="80" name="cpd:C20683" type="compound"
        link="https://www.kegg.jp/dbget-bin/www_bget?C20683">
        <graphics name="C20683" fgcolor="#000000" bgcolor="#FFFFFF"
             type="circle" x="414" y="351" width="8" height="8"/>
    </entry>
    <entry id="83" name="ko:K01435" type="ortholog" reaction="rn:R01077"
        link="https://www.kegg.jp/dbget-bin/www_bget?K01435">
        <graphics name="K01435" fgcolor="#000000" bgcolor="#FFFFFF"
             type="rectangle" x="281" y="831" width="46" height="17"/>
    </entry>
    <entry id="84" name="cpd:C20384" type="compound"
        link="https://www.kegg.jp/dbget-bin/www_bget?C20384">
        <graphics name="C20384" fgcolor="#000000" bgcolor="#FFFFFF"
             type="circle" x="578" y="884" width="8" height="8"/>
    </entry>
    <entry id="85" name="cpd:C20385" type="compound"
        link="https://www.kegg.jp/dbget-bin/www_bget?C20385">
        <graphics name="C20385" fgcolor="#000000" bgcolor="#FFFFFF"
             type="circle" x="644" y="884" width="8" height="8"/>
    </entry>
    <entry id="89" name="path:cla00061" type="map"
        link="https://www.kegg.jp/dbget-bin/www_bget?cla00061">
        <graphics name="Fatty acid biosynthesis" fgcolor="#000000" bgcolor="#FFFFFF"
             type="roundrectangle" x="119" y="930" width="123" height="25"/>
    </entry>
    <entry id="90" name="path:cla00061" type="map"
        link="https://www.kegg.jp/dbget-bin/www_bget?cla00061">
        <graphics name="Fatty acid biosynthesis" fgcolor="#000000" bgcolor="#FFFFFF"
             type="roundrectangle" x="413" y="111" width="123" height="25"/>
    </entry>
    <entry id="94" name="cpd:C20386" type="compound"
        link="https://www.kegg.jp/dbget-bin/www_bget?C20386">
        <graphics name="C20386" fgcolor="#000000" bgcolor="#FFFFFF"
             type="circle" x="513" y="791" width="8" height="8"/>
    </entry>
    <entry id="96" name="cpd:C20387" type="compound"
        link="https://www.kegg.jp/dbget-bin/www_bget?C20387">
        <graphics name="C20387" fgcolor="#000000" bgcolor="#FFFFFF"
             type="circle" x="579" y="791" width="8" height="8"/>
    </entry>
    <entry id="98" name="ko:K08351" type="ortholog" reaction="rn:R10127"
        link="https://www.kegg.jp/dbget-bin/www_bget?K08351">
        <graphics name="K08351" fgcolor="#000000" bgcolor="#FFFFFF"
             type="rectangle" x="464" y="800" width="46" height="17"/>
    </entry>
    <entry id="100" name="cpd:C00086" type="compound"
        link="https://www.kegg.jp/dbget-bin/www_bget?C00086">
        <graphics name="C00086" fgcolor="#000000" bgcolor="#FFFFFF"
             type="circle" x="644" y="927" width="8" height="8"/>
    </entry>
    <entry id="101" name="ko:K00647" type="ortholog" reaction="rn:R10115"
        link="https://www.kegg.jp/dbget-bin/www_bget?K00647">
        <graphics name="K00647" fgcolor="#000000" bgcolor="#FFFFFF"
             type="rectangle" x="153" y="229" width="46" height="17"/>
    </entry>
    <entry id="102" name="cla:CLA_0286" type="gene" reaction="rn:R10115"
        link="https://www.kegg.jp/dbget-bin/www_bget?cla:CLA_0286">
        <graphics name="fabF" fgcolor="#000000" bgcolor="#BFFFBF"
             type="rectangle" x="203" y="229" width="46" height="17"/>
    </entry>
    <entry id="103" name="ko:K19563" type="ortholog" reaction="rn:R10699"
        link="https://www.kegg.jp/dbget-bin/www_bget?K19563">
        <graphics name="K19563" fgcolor="#000000" bgcolor="#FFFFFF"
             type="rectangle" x="439" y="558" width="46" height="17"/>
    </entry>
    <entry id="104" name="cpd:C22458" type="compound"
        link="https://www.kegg.jp/dbget-bin/www_bget?C22458">
        <graphics name="C22458" fgcolor="#000000" bgcolor="#FFFFFF"
             type="circle" x="414" y="659" width="8" height="8"/>
    </entry>
    <entry id="106" name="cla:CLA_1389" type="gene" reaction="rn:R12933"
        link="https://www.kegg.jp/dbget-bin/www_bget?cla:CLA_1389">
        <graphics name="bioD" fgcolor="#000000" bgcolor="#BFFFBF"
             type="rectangle" x="414" y="622" width="46" height="17"/>
    </entry>
    <entry id="108" name="ko:K25570" type="ortholog" reaction="rn:R12935"
        link="https://www.kegg.jp/dbget-bin/www_bget?K25570">
        <graphics name="K25570" fgcolor="#000000" bgcolor="#FFFFFF"
             type="rectangle" x="504" y="595" width="46" height="17"/>
    </entry>
    <relation entry1="52" entry2="90" type="maplink">
        <subtype name="compound" value="49"/>
    </relation>
    <relation entry1="52" entry2="102" type="ECrel">
        <subtype name="compound" value="50"/>
    </relation>
    <relation entry1="102" entry2="56" type="ECrel">
        <subtype name="compound" value="54"/>
    </relation>
    <relation entry1="56" entry2="59" type="ECrel">
        <subtype name="compound" value="57"/>
    </relation>
    <relation entry1="77" entry2="70" type="ECrel">
        <subtype name="compound" value="68"/>
    </relation>
    <relation entry1="70" entry2="73" type="ECrel">
        <subtype name="compound" value="71"/>
    </relation>
    <relation entry1="45" entry2="48" type="ECrel">
        <subtype name="compound" value="43"/>
    </relation>
    <relation entry1="48" entry2="35" type="ECrel">
        <subtype name="compound" value="7"/>
    </relation>
    <relation entry1="48" entry2="37" type="ECrel">
        <subtype name="compound" value="7"/>
    </relation>
    <relation entry1="35" entry2="37" type="ECrel">
        <subtype name="compound" value="7"/>
    </relation>
    <relation entry1="34" entry2="33" type="ECrel">
        <subtype name="compound" value="8"/>
    </relation>
    <relation entry1="33" entry2="31" type="ECrel">
        <subtype name="compound" value="10"/>
    </relation>
    <relation entry1="29" entry2="89" type="maplink">
        <subtype name="compound" value="15"/>
    </relation>
    <relation entry1="4" entry2="2" type="maplink">
        <subtype name="compound" value="11"/>
    </relation>
    <relation entry1="35" entry2="106" type="ECrel">
        <subtype name="compound" value="9"/>
    </relation>
    <reaction id="29" name="rn:R05145" type="irreversible">
        <substrate id="14" name="cpd:C05921"/>
        <product id="15" name="cpd:C06250"/>
    </reaction>
    <reaction id="31" name="rn:R01074" type="irreversible">
        <substrate id="10" name="cpd:C00120"/>
        <product id="14" name="cpd:C05921"/>
    </reaction>
    <reaction id="33" name="rn:R01078" type="irreversible">
        <substrate id="8" name="cpd:C01909"/>
        <product id="10" name="cpd:C00120"/>
    </reaction>
    <reaction id="34" name="rn:R12934" type="irreversible">
        <substrate id="104" name="cpd:C22458"/>
        <product id="8" name="cpd:C01909"/>
    </reaction>
    <reaction id="35" name="rn:R03231" type="irreversible">
        <substrate id="7" name="cpd:C01092"/>
        <product id="9" name="cpd:C01037"/>
    </reaction>
    <reaction id="37" name="rn:R03210" type="irreversible">
        <substrate id="6" name="cpd:C01063"/>
        <product id="7" name="cpd:C01092"/>
    </reaction>
    <reaction id="45" name="rn:R09725" type="irreversible">
        <substrate id="46" name="cpd:C19846"/>
        <product id="43" name="cpd:C19845"/>
    </reaction>
    <reaction id="48" name="rn:R10124" type="irreversible">
        <substrate id="43" name="cpd:C19845"/>
        <product id="7" name="cpd:C01092"/>
    </reaction>
    <reaction id="52" name="rn:R09543" type="irreversible">
        <substrate id="49" name="cpd:C01209"/>
        <product id="50" name="cpd:C19673"/>
    </reaction>
    <reaction id="56" name="rn:R10116" type="irreversible">
        <substrate id="54" name="cpd:C20372"/>
        <product id="57" name="cpd:C20373"/>
    </reaction>
    <reaction id="59" name="rn:R10117" type="irreversible">
        <substrate id="57" name="cpd:C20373"/>
        <product id="60" name="cpd:C20374"/>
    </reaction>
    <reaction id="73" name="rn:R10121" type="irreversible">
        <substrate id="71" name="cpd:C20377"/>
        <product id="74" name="cpd:C20378"/>
    </reaction>
    <reaction id="70" name="rn:R10120" type="irreversible">
        <substrate id="68" name="cpd:C20376"/>
        <product id="71" name="cpd:C20377"/>
    </reaction>
    <reaction id="77" name="rn:R10119" type="irreversible">
        <substrate id="49" name="cpd:C01209"/>
        <substrate id="63" name="cpd:C20375"/>
        <product id="68" name="cpd:C20376"/>
    </reaction>
    <reaction id="102" name="rn:R10115" type="irreversible">
        <substrate id="49" name="cpd:C01209"/>
        <substrate id="50" name="cpd:C19673"/>
        <product id="54" name="cpd:C20372"/>
    </reaction>
    <reaction id="106" name="rn:R12933" type="irreversible">
        <substrate id="9" name="cpd:C01037"/>
        <product id="104" name="cpd:C22458"/>
    </reaction>
</pathway>
